pdm/pep517/__init__.py
pdm/pep517/_vendor/__init__.py
pdm/pep517/_vendor/boolean/__init__.py
pdm/pep517/_vendor/boolean/boolean.py
pdm/pep517/_vendor/boolean.py.LICENSE.txt
pdm/pep517/_vendor/cerberus/LICENSE
pdm/pep517/_vendor/cerberus/__init__.py
pdm/pep517/_vendor/cerberus/errors.py
pdm/pep517/_vendor/cerberus/platform.py
pdm/pep517/_vendor/cerberus/schema.py
pdm/pep517/_vendor/cerberus/utils.py
pdm/pep517/_vendor/cerberus/validator.py
pdm/pep517/_vendor/license_expression/__init__.py
pdm/pep517/_vendor/license_expression/_pyahocorasick.ABOUT
pdm/pep517/_vendor/license_expression/_pyahocorasick.py
pdm/pep517/_vendor/license_expression/apache-2.0.LICENSE
pdm/pep517/_vendor/license_expression/cc-by-4.0.LICENSE
pdm/pep517/_vendor/license_expression/data/cc-by-4.0.LICENSE
pdm/pep517/_vendor/license_expression/data/license_key_index.json.ABOUT
pdm/pep517/_vendor/license_expression/data/scancode-licensedb-index.json
pdm/pep517/_vendor/packaging/LICENSE
pdm/pep517/_vendor/packaging/LICENSE.APACHE
pdm/pep517/_vendor/packaging/LICENSE.BSD
pdm/pep517/_vendor/packaging/__init__.py
pdm/pep517/_vendor/packaging/_elffile.py
pdm/pep517/_vendor/packaging/_manylinux.py
pdm/pep517/_vendor/packaging/_musllinux.py
pdm/pep517/_vendor/packaging/_parser.py
pdm/pep517/_vendor/packaging/_structures.py
pdm/pep517/_vendor/packaging/_tokenizer.py
pdm/pep517/_vendor/packaging/markers.py
pdm/pep517/_vendor/packaging/py.typed
pdm/pep517/_vendor/packaging/requirements.py
pdm/pep517/_vendor/packaging/specifiers.py
pdm/pep517/_vendor/packaging/tags.py
pdm/pep517/_vendor/packaging/utils.py
pdm/pep517/_vendor/packaging/version.py
pdm/pep517/_vendor/tomli/LICENSE
pdm/pep517/_vendor/tomli/__init__.py
pdm/pep517/_vendor/tomli/_parser.py
pdm/pep517/_vendor/tomli/_re.py
pdm/pep517/_vendor/tomli/_types.py
pdm/pep517/_vendor/tomli/py.typed
pdm/pep517/_vendor/tomli_w/LICENSE
pdm/pep517/_vendor/tomli_w/__init__.py
pdm/pep517/_vendor/tomli_w/_writer.py
pdm/pep517/_vendor/tomli_w/py.typed
pdm_pep517-1.1.4.dist-info/WHEEL
pdm_pep517-1.1.4.dist-info/METADATA
pdm_pep517-1.1.4.dist-info/licenses/LICENSE
pdm_pep517-1.1.4.dist-info/RECORD
