Metadata-Version: 2.1
Name: pdm-pep517
Version: 1.1.4
Summary: A PEP 517 backend for PDM that supports PEP 621 metadata
License: MIT
Keywords: packaging,PEP 517,build
Author-email: Frost Ming <mianghong@gmail.com>
Requires-Python: >=3.7
Classifier: Development Status :: 5 - Production/Stable
Classifier: Programming Language :: Python :: 3
Classifier: Programming Language :: Python :: 3.10
Classifier: Programming Language :: Python :: 3.11
Classifier: Programming Language :: Python :: 3.7
Classifier: Programming Language :: Python :: 3.8
Classifier: Programming Language :: Python :: 3.9
Classifier: Topic :: Software Development :: Build Tools
Project-URL: homepage, https://pdm.fming.dev
Project-URL: repository, https://github.com/pdm-project/pdm-pep517
